{
  "project_info": {
    "project_number": "508647598899",
    "project_id": "beyondschool-test",
    "storage_bucket": "beyondschool-test.appspot.com"
  },
  "client": [
    {
      "client_info": {
        "mobilesdk_app_id": "1:508647598899:android:02488e90f9ceedffe6ec46",
        "android_client_info": {
          "package_name": "com.maths.beyond_school_280720220930"
        }
      },
      "oauth_client": [
        {
          "client_id": "508647598899-a1kr235ug5q7gt8u0ajd2qcsku0m3trk.apps.googleusercontent.com",
          "client_type": 3
        }
      ],
      "api_key": [
        {
          "current_key": "AIzaSyDlKhasMdG8BLQrJZr16rRAT_XVZeT4JiY"
        }
      ],
      "services": {
        "appinvite_service": {
          "other_platform_oauth_client": [
            {
              "client_id": "508647598899-a1kr235ug5q7gt8u0ajd2qcsku0m3trk.apps.googleusercontent.com",
              "client_type": 3
            }
          ]
        }
      }
    }
  ],
  "configuration_version": "1"
}